flight_optimizer/__init__.py
flight_optimizer/cli.py
flight_optimizer/dataclasses.py
flight_optimizer/utils.py
tests/__init__.py
tests/fixtures.py
tests/outputs.py
tests/test_flight_optimizer.py
flight_optimizer-0.2.0.dist-info/METADATA
flight_optimizer-0.2.0.dist-info/WHEEL
flight_optimizer-0.2.0.dist-info/entry_points.txt
flight_optimizer-0.2.0.dist-info/top_level.txt
flight_optimizer-0.2.0.dist-info/RECORD
