Metadata-Version: 2.1
Name: flight-optimizer
Version: 0.2.0
Summary: Package that searches for the cheapest airplane flights per kilometer.
Home-page: UNKNOWN
Author: Erik Duisheev
Author-email: erik.duisheev@gmail.com
License: UNLICENSE
Platform: UNKNOWN
Requires-Python: >=3.6,<4.0
Requires-Dist: click (==7.1.2)
Requires-Dist: pytest (==5.4.3)
Requires-Dist: pytest-mock (==3.1.1)
Requires-Dist: dataclasses (==0.6)
Requires-Dist: requests (==2.24.0)
Requires-Dist: haversine (==2.2.0)
